[{"id": "00161e5d-2ec2-470d-8f1f-dcb2b5de22a6", "serialId": 268, "name": "Whitebit", "slug": "whitebit", "exchangeType": "centralized", "marketData": {"volume24Hours": 2198454357.0722995, "volume48To24Hours": 2581979893.05925, "percentChangeVolume24Hours": -14.853931938739132, "averageDeviationFromVwapPercent": 0.06737441683049318, "lastTradeAt": "2024-04-19T00:20:00Z"}, "attributes": {"spotMarkets": 366, "spotAssets": 247}}, {"id": "0146e251-3361-449b-811e-5db5721f3f96", "serialId": 75, "name": "Binance US", "slug": "binanceus", "exchangeType": "centralized", "marketData": {"volume24Hours": 13424423.093633072, "volume48To24Hours": 19883783.484143164, "percentChangeVolume24Hours": -32.48556994025446, "averageDeviationFromVwapPercent": 0.1053906556077005, "lastTradeAt": "2024-04-19T00:20:00Z"}, "attributes": {"spotMarkets": 174, "spotAssets": 159}}, {"id": "04abf633-b1d3-48b4-be78-73222e5757e8", "serialId": 38, "name": "CEX.IO", "slug": "cexio", "exchangeType": "centralized", "marketData": {"volume24Hours": 17322135.65633684, "volume48To24Hours": 8692260.847739855, "percentChangeVolume24Hours": 99.28228063750421, "averageDeviationFromVwapPercent": 0.004587726522694892, "lastTradeAt": "2024-04-19T00:20:00Z"}, "attributes": {"spotMarkets": 480, "spotAssets": 183}}, {"id": "06b54b6d-1674-42b4-a468-4ef574be37ca", "serialId": 31, "name": "Currency.com", "slug": "currency-com", "exchangeType": "centralized", "marketData": {"volume24Hours": 722842.4958495756, "volume48To24Hours": 1251424.8774863353, "percentChangeVolume24Hours": -42.23844284592556, "averageDeviationFromVwapPercent": 0.007638814634016937, "lastTradeAt": "2024-04-19T00:16:00Z"}, "attributes": {"spotMarkets": 67, "spotAssets": 49}}, {"id": "077fe1eb-c995-4aad-9dbe-60daec257b02", "serialId": 175, "name": "Probit", "slug": "probit", "exchangeType": "centralized", "marketData": {"volume24Hours": 385671282.63290304, "volume48To24Hours": 635558311.8280343, "percentChangeVolume24Hours": -39.317718696242025, "averageDeviationFromVwapPercent": 0.28795399889837303, "lastTradeAt": "2024-04-19T00:20:00Z"}, "attributes": {"spotMarkets": 207, "spotAssets": 168}}, {"id": "0db82dc0-fa38-4831-b50a-3ac803de1754", "serialId": 112, "name": "Bybit", "slug": "bybit", "exchangeType": "centralized", "marketData": {"volume24Hours": 5102758146.447797, "volume48To24Hours": 5261698825.804784, "percentChangeVolume24Hours": -3.0207103184526494, "averageDeviationFromVwapPercent": 0.046158078957186974, "lastTradeAt": "2024-04-19T00:20:00Z"}, "attributes": {"spotMarkets": 477, "spotAssets": 420}}, {"id": "0dc16437-463b-48ec-9fd1-50b9fdcedb8c", "serialId": 52, "name": "HitBTC", "slug": "hitbtc", "exchangeType": "centralized", "marketData": {"volume24Hours": 279119465.73802626, "volume48To24Hours": 269419954.76711076, "percentChangeVolume24Hours": 3.6001457202009584, "averageDeviationFromVwapPercent": -0.4467467042559208, "lastTradeAt": "2024-04-19T00:20:00Z"}, "attributes": {"spotMarkets": 530, "spotAssets": 284}}, {"id": "12dd97ab-e7a6-472b-9b9d-73169c2d08e3", "serialId": 169, "name": "Indodax", "slug": "indodax", "exchangeType": "centralized", "marketData": {"volume24Hours": 213026.4462711003, "volume48To24Hours": 259378.56716760382, "percentChangeVolume24Hours": -17.870451441946607, "averageDeviationFromVwapPercent": 0.22672924787204668, "lastTradeAt": "2024-04-19T00:19:00Z"}, "attributes": {"spotMarkets": 16, "spotAssets": 17}}, {"id": "17233647-a3fe-49dc-be8d-60857e76e4ae", "serialId": 7, "name": "Btcbox", "slug": "btcbox", "exchangeType": "centralized", "marketData": {"volume24Hours": 12404771.011144169, "volume48To24Hours": 12998329.876727995, "percentChangeVolume24Hours": -4.566424080731513, "averageDeviationFromVwapPercent": -0.03507939117916879, "lastTradeAt": "2024-04-19T00:20:00Z"}, "attributes": {"spotMarkets": 7, "spotAssets": 8}}, {"id": "174e0471-1033-4e12-97d5-9f234ed21142", "serialId": 45, "name": "LBank", "slug": "lbank", "exchangeType": "centralized", "marketData": {"volume24Hours": 186160999.61511493, "volume48To24Hours": 226269922.01134217, "percentChangeVolume24Hours": -17.726139665269656, "averageDeviationFromVwapPercent": 0.13942240647215895, "lastTradeAt": "2024-04-19T00:19:00Z"}, "attributes": {"spotMarkets": 312, "spotAssets": 308}}, {"id": "181f44f6-f9b7-4c11-9e44-7c7f803d808e", "serialId": 44, "name": "Coinbase Exchange", "slug": "coinbase", "exchangeType": "centralized", "marketData": {"volume24Hours": 2656432296.9750547, "volume48To24Hours": 3390213917.4956236, "percentChangeVolume24Hours": -21.644109734014037, "averageDeviationFromVwapPercent": 0.014145344352788745, "lastTradeAt": "2024-04-19T00:20:00Z"}, "attributes": {"spotMarkets": 379, "spotAssets": 253}}, {"id": "19e0fd2a-2226-4552-80da-749a66953588", "serialId": 88, "name": "Curve", "slug": "curve", "exchangeType": "decentralized", "marketData": {"volume24Hours": 307289366.5510794, "volume48To24Hours": 297979900.59393317, "percentChangeVolume24Hours": 3.12419258432888, "averageDeviationFromVwapPercent": 0.022316827730397955, "lastTradeAt": "2024-04-19T00:20:00Z"}, "attributes": {"spotMarkets": 146, "spotAssets": 99}}, {"id": "1f8cff02-1906-4654-b8cc-8aa4d21ba0fe", "serialId": 62, "name": "Upbit", "slug": "upbit", "exchangeType": "centralized", "marketData": {"volume24Hours": 2368673038.707656, "volume48To24Hours": 2241746031.2401614, "percentChangeVolume24Hours": 5.661970878890188, "averageDeviationFromVwapPercent": 0.005191632976902578, "lastTradeAt": "2024-04-19T00:20:00Z"}, "attributes": {"spotMarkets": 302, "spotAssets": 193}}, {"id": "2087a29e-6a27-4d51-ba3b-d9f112f93c38", "serialId": 69, "name": "YoBit", "slug": "yobit", "exchangeType": "centralized", "marketData": {"volume24Hours": 111114911.96740581, "volume48To24Hours": 122257462.42415641, "percentChangeVolume24Hours": -9.114004360807822, "averageDeviationFromVwapPercent": 0.9979226212131702, "lastTradeAt": "2024-04-19T00:19:00Z"}, "attributes": {"spotMarkets": 57, "spotAssets": 21}}, {"id": "2128b895-e571-46fa-9c3c-40c3feb6a45b", "serialId": 266, "name": "Ascendex", "slug": "ascendex", "exchangeType": "centralized", "marketData": {"volume24Hours": 35189851.695583954, "volume48To24Hours": 174547768.09652045, "percentChangeVolume24Hours": -79.83941468897793, "averageDeviationFromVwapPercent": 0.11034150366412773, "lastTradeAt": "2024-04-19T00:20:00Z"}, "attributes": {"spotMarkets": 336, "spotAssets": 304}}, {"id": "28de284c-51c4-44dc-97bd-18c85651891d", "serialId": 114, "name": "Dcoin", "slug": "dcoin", "exchangeType": "centralized", "marketData": {"volume24Hours": 56410948.96970769, "volume48To24Hours": 59743508.05913933, "percentChangeVolume24Hours": -5.578110823577327, "averageDeviationFromVwapPercent": -0.016503702976689363, "lastTradeAt": "2024-04-19T00:20:00Z"}, "attributes": {"spotMarkets": 17, "spotAssets": 18}}, {"id": "2b473c47-ee9b-4c00-821f-ea5f6a66f063", "serialId": 51, "name": "CoinEx", "slug": "coinex", "exchangeType": "centralized", "marketData": {"volume24Hours": 57131336.35034561, "volume48To24Hours": 69690699.3477636, "percentChangeVolume24Hours": -18.021576932017144, "averageDeviationFromVwapPercent": -0.0073689463616593304, "lastTradeAt": "2024-04-19T00:20:00Z"}, "attributes": {"spotMarkets": 1047, "spotAssets": 774}}, {"id": "2b482c0b-592c-47a3-bc24-33c8788feea7", "serialId": 265, "name": "Bitrue", "slug": "bitrue", "exchangeType": "centralized", "marketData": {"volume24Hours": 2053367476.3157945, "volume48To24Hours": 2219859981.7911687, "percentChangeVolume24Hours": -7.500135451833054, "averageDeviationFromVwapPercent": -0.08592513093506991, "lastTradeAt": "2024-04-19T00:20:00Z"}, "attributes": {"spotMarkets": 739, "spotAssets": 499}}, {"id": "2d9d2493-31ae-47b0-9943-dae8be78559d", "serialId": 150, "name": "bitFlyer US", "slug": "bitflyer-us", "exchangeType": "centralized", "marketData": {"volume24Hours": 106046709.90439288, "volume48To24Hours": 140600126.48029953, "percentChangeVolume24Hours": -24.57566535741927, "averageDeviationFromVwapPercent": 0.025415796191530074, "lastTradeAt": "2024-04-19T00:20:00Z"}, "attributes": {"spotMarkets": 4, "spotAssets": 4}}, {"id": "3043f65e-a405-4ca5-84f7-35f0e0bf0c9c", "serialId": 161, "name": "CoinsBit", "slug": "coinsbit", "exchangeType": "centralized", "marketData": {"volume24Hours": 871207841.7545725, "volume48To24Hours": 1053382732.6365805, "percentChangeVolume24Hours": -17.294273509309434, "averageDeviationFromVwapPercent": 0.029323241680531256, "lastTradeAt": "2024-04-19T00:20:00Z"}, "attributes": {"spotMarkets": 73, "spotAssets": 42}}, {"id": "304489b4-b58b-4db7-bca9-8a1ab191773d", "serialId": 155, "name": "One Trading", "slug": "bitpanda-pro", "exchangeType": "centralized", "marketData": {"volume24Hours": 5717499.778424587, "volume48To24Hours": 8353405.415554159, "percentChangeVolume24Hours": -31.55486302893283, "averageDeviationFromVwapPercent": -0.023751309912274296, "lastTradeAt": "2024-04-19T00:19:00Z"}, "attributes": {"spotMarkets": 10, "spotAssets": 6}}, {"id": "3663f00d-91fc-48a2-98a2-8af76325927a", "serialId": 37, "name": "Bitstamp", "slug": "bitstamp", "exchangeType": "centralized", "marketData": {"volume24Hours": 291185216.5854104, "volume48To24Hours": 352100859.7140169, "percentChangeVolume24Hours": -17.300623229969776, "averageDeviationFromVwapPercent": 0.1422110670552859, "lastTradeAt": "2024-04-19T00:20:00Z"}, "attributes": {"spotMarkets": 172, "spotAssets": 85}}, {"id": "37bbe16b-1864-4cda-a056-f6483cd8fa52", "serialId": 30, "name": "Luno", "slug": "luno", "exchangeType": "centralized", "marketData": {"volume24Hours": 440890.4360264121, "volume48To24Hours": 729932.4872798201, "percentChangeVolume24Hours": -39.59846373334573, "averageDeviationFromVwapPercent": 0.3049499345551032, "lastTradeAt": "2024-04-19T00:20:00Z"}, "attributes": {"spotMarkets": 26, "spotAssets": 19}}, {"id": "38ba31ae-8db7-4f81-82a7-cadfff74cc4a", "serialId": 262, "name": "Phoenix", "slug": "phoenix", "exchangeType": "decentralized", "marketData": {"volume24Hours": 0, "volume48To24Hours": 140307088.71383592, "percentChangeVolume24Hours": -100, "averageDeviationFromVwapPercent": 0.11211006093046479, "lastTradeAt": "2024-04-17T23:45:00Z"}, "attributes": {"spotMarkets": 23, "spotAssets": 18}}, {"id": "4173177d-94f8-4ab5-9f67-5dc67663f88d", "serialId": 80, "name": "Huobi Global", "slug": "huobi", "exchangeType": "centralized", "marketData": {"volume24Hours": 2238637217.3418736, "volume48To24Hours": 2267458070.3726287, "percentChangeVolume24Hours": -1.2710644314590873, "averageDeviationFromVwapPercent": 0.09790368378257698, "lastTradeAt": "2024-04-19T00:20:00Z"}, "attributes": {"spotMarkets": 726, "spotAssets": 661}}, {"id": "42f98807-bdd8-426e-a5d8-0556af0c17e0", "serialId": 74, "name": "Bithumb", "slug": "bithumb", "exchangeType": "centralized", "marketData": {"volume24Hours": 1113129135.3822353, "volume48To24Hours": 1319037215.4293938, "percentChangeVolume24Hours": -15.610482982478096, "averageDeviationFromVwapPercent": -0.003211653716341323, "lastTradeAt": "2024-04-19T00:20:00Z"}, "attributes": {"spotMarkets": 277, "spotAssets": 271}}, {"id": "45c6d9e2-8105-4fc0-9974-aa4bab98f7cb", "serialId": 1793790, "name": "Apeswap", "slug": "apeswap", "exchangeType": "decentralized", "marketData": {"volume24Hours": 287366.1091566267, "volume48To24Hours": 446519.57067323604, "percentChangeVolume24Hours": -35.643109948495, "averageDeviationFromVwapPercent": -0.07188437080179678, "lastTradeAt": "2024-04-19T00:19:00Z"}, "attributes": {"spotMarkets": 284, "spotAssets": 189}}, {"id": "46ebd2f8-fe09-4e8e-bc5c-b145a0d59a63", "serialId": 108, "name": "Bullish", "slug": "bullish", "exchangeType": "centralized", "marketData": {"volume24Hours": 1367856067.8590453, "volume48To24Hours": 1939817904.7229512, "percentChangeVolume24Hours": -29.485336508717026, "averageDeviationFromVwapPercent": 0.007048232410008188, "lastTradeAt": "2024-04-19T00:20:00Z"}, "attributes": {"spotMarkets": 35, "spotAssets": 32}}, {"id": "4dfd5675-8b84-47f2-9c30-43101af79c30", "serialId": 252, "name": "Raydium (CLMM)", "slug": "raydium-clmm", "exchangeType": "decentralized", "marketData": {"volume24Hours": 69887009.5694242, "volume48To24Hours": 44365691.3841965, "percentChangeVolume24Hours": 57.524896804197326, "averageDeviationFromVwapPercent": 0.2903524831387599, "lastTradeAt": "2024-04-19T00:20:00Z"}, "attributes": {"spotMarkets": 215, "spotAssets": 141}}, {"id": "4ff8d5c9-a716-4948-b2ee-7909e50886e6", "serialId": 255, "name": "Lifinity v2", "slug": "lifinity-v2", "exchangeType": "decentralized", "marketData": {"volume24Hours": 218382349.127561, "volume48To24Hours": 114960459.06270194, "percentChangeVolume24Hours": 89.96301068043797, "averageDeviationFromVwapPercent": -0.033670836200445975, "lastTradeAt": "2024-04-19T00:20:00Z"}, "attributes": {"spotMarkets": 16, "spotAssets": 16}}, {"id": "5204836b-f5ac-478e-bc50-b51c56cb97c6", "serialId": 42, "name": "Kraken", "slug": "kraken", "exchangeType": "centralized", "marketData": {"volume24Hours": 1184609861.9149835, "volume48To24Hours": 1283098604.6829736, "percentChangeVolume24Hours": -7.675851443414561, "averageDeviationFromVwapPercent": 0.19338242994940152, "lastTradeAt": "2024-04-19T00:20:00Z"}, "attributes": {"spotMarkets": 647, "spotAssets": 252}}, {"id": "55318173-5bb2-4b8b-a692-312909189b4a", "serialId": 256, "name": "Orca (whirlpool)", "slug": "orca-whirlpool", "exchangeType": "decentralized", "marketData": {"volume24Hours": 331986249.5723414, "volume48To24Hours": 191676022.59389552, "percentChangeVolume24Hours": 73.20176257816111, "averageDeviationFromVwapPercent": 0.02103157984698081, "lastTradeAt": "2024-04-19T00:20:00Z"}, "attributes": {"spotMarkets": 929, "spotAssets": 444}}, {"id": "5aada84c-4543-4a4e-92c6-b1d325ce557c", "serialId": 1793587, "name": "Solarbeam", "slug": "solarbeam", "exchangeType": "decentralized", "marketData": {"volume24Hours": 19232.06614743774, "volume48To24Hours": 32309.41746387709, "percentChangeVolume24Hours": -40.47535468895477, "averageDeviationFromVwapPercent": 1.3286370842872335, "lastTradeAt": "2024-04-19T00:16:00Z"}, "attributes": {"spotMarkets": 3, "spotAssets": 3}}, {"id": "5e3d6b48-b425-471e-918b-d0c988eae296", "serialId": 178, "name": "VALR", "slug": "valr", "exchangeType": "centralized", "marketData": {"volume24Hours": 1293113.6009821866, "volume48To24Hours": 1650787.136877074, "percentChangeVolume24Hours": -21.666847766425352, "averageDeviationFromVwapPercent": 0.011467317382936113, "lastTradeAt": "2024-04-19T00:06:00Z"}, "attributes": {"spotMarkets": 16, "spotAssets": 12}}, {"id": "626f0db0-3278-471f-980c-1d23896cc71d", "serialId": 61, "name": "Korbit", "slug": "korbit", "exchangeType": "centralized", "marketData": {"volume24Hours": 11145257.110146191, "volume48To24Hours": 12309829.73797734, "percentChangeVolume24Hours": -9.460509630269701, "averageDeviationFromVwapPercent": 0.40662252812719796, "lastTradeAt": "2024-04-19T00:19:00Z"}, "attributes": {"spotMarkets": 136, "spotAssets": 137}}, {"id": "658df94b-6214-4782-81cd-a092d7e63e11", "serialId": 90, "name": "Balancer (v2)", "slug": "balancer-v2", "exchangeType": "decentralized", "marketData": {"volume24Hours": 55086234.68955631, "volume48To24Hours": 80070832.46357056, "percentChangeVolume24Hours": -31.203119794441225, "averageDeviationFromVwapPercent": 0.10358979598735828, "lastTradeAt": "2024-04-19T00:18:00Z"}, "attributes": {"spotMarkets": 105, "spotAssets": 98}}, {"id": "65d7db09-764a-41a8-ac63-50a2d296f874", "serialId": 84, "name": "Uniswap (v3)", "slug": "uniswap-v3", "exchangeType": "decentralized", "marketData": {"volume24Hours": 1503271160.9633093, "volume48To24Hours": 1715330004.319742, "percentChangeVolume24Hours": -12.362568300117273, "averageDeviationFromVwapPercent": -0.044153962846877164, "lastTradeAt": "2024-04-19T00:20:00Z"}, "attributes": {"spotMarkets": 1719, "spotAssets": 1215}}, {"id": "66dfc7e9-e098-4143-a462-cf2579b31cb5", "serialId": 39, "name": "BigONE", "slug": "bigone", "exchangeType": "centralized", "marketData": {"volume24Hours": 613509373.7782015, "volume48To24Hours": 724264547.8165649, "percentChangeVolume24Hours": -15.292088280760986, "averageDeviationFromVwapPercent": -0.04319808440218543, "lastTradeAt": "2024-04-19T00:20:00Z"}, "attributes": {"spotMarkets": 99, "spotAssets": 92}}, {"id": "69bb6f71-5614-4b8d-92fd-0d0b4e87f2c7", "serialId": 76, "name": "Zaif", "slug": "zaif", "exchangeType": "centralized", "marketData": {"volume24Hours": 262422090.71687147, "volume48To24Hours": 287640619.24152243, "percentChangeVolume24Hours": -8.767373881738095, "averageDeviationFromVwapPercent": -0.0944873304855312, "lastTradeAt": "2024-04-19T00:20:00Z"}, "attributes": {"spotMarkets": 16, "spotAssets": 12}}, {"id": "6b7daad8-c6f0-48fd-a3db-e1276f03918d", "serialId": 72, "name": "OKX", "slug": "okx", "exchangeType": "centralized", "marketData": {"volume24Hours": 3658698781.514608, "volume48To24Hours": 4574230614.201511, "percentChangeVolume24Hours": -20.014990714383142, "averageDeviationFromVwapPercent": 0.011573998096002704, "lastTradeAt": "2024-04-19T00:20:00Z"}, "attributes": {"spotMarkets": 499, "spotAssets": 324}}, {"id": "6efbfc8a-18c9-4c6f-aa78-feea100521cf", "serialId": 85, "name": "Uniswap (v2)", "slug": "uniswap", "exchangeType": "decentralized", "marketData": {"volume24Hours": 153508977.41767877, "volume48To24Hours": 189358435.82039434, "percentChangeVolume24Hours": -18.932063019742422, "averageDeviationFromVwapPercent": 0.25066473644245874, "lastTradeAt": "2024-04-19T00:20:00Z"}, "attributes": {"spotMarkets": 2229, "spotAssets": 2102}}, {"id": "6f4b6490-e55a-48c1-b079-d2983366ae36", "serialId": 32, "name": "itBit", "slug": "itbit", "exchangeType": "centralized", "marketData": {"volume24Hours": 21236252.49093985, "volume48To24Hours": 26993435.638380002, "percentChangeVolume24Hours": -21.328085926396234, "averageDeviationFromVwapPercent": 0.0588908775288365, "lastTradeAt": "2024-04-19T00:20:00Z"}, "attributes": {"spotMarkets": 10, "spotAssets": 11}}, {"id": "74079b89-fc6d-499d-84a2-0bb1bc1ed6be", "serialId": 264, "name": "Bitget", "slug": "bitget", "exchangeType": "centralized", "marketData": {"volume24Hours": 2234302720.338849, "volume48To24Hours": 2695105598.897676, "percentChangeVolume24Hours": -17.09776710594567, "averageDeviationFromVwapPercent": 0.0868809848668754, "lastTradeAt": "2024-04-19T00:20:00Z"}, "attributes": {"spotMarkets": 648, "spotAssets": 587}}, {"id": "743340f0-f5e0-4c4e-a472-7eda9f47e34c", "serialId": 116, "name": "Bancor (v3)", "slug": "bancor-v3", "exchangeType": "decentralized", "marketData": {"volume24Hours": 90934.98657193346, "volume48To24Hours": 39430.686102365784, "percentChangeVolume24Hours": 130.61984347890282, "averageDeviationFromVwapPercent": 1.5383837821936854, "lastTradeAt": "2024-04-18T23:24:00Z"}, "attributes": {"spotMarkets": 9, "spotAssets": 8}}, {"id": "75a38c76-4ae7-4f06-9e5b-6e11eb70bdab", "serialId": 107, "name": "DigiFinex", "slug": "digifinex", "exchangeType": "centralized", "marketData": {"volume24Hours": 1423483150.3142796, "volume48To24Hours": 1712669495.9484482, "percentChangeVolume24Hours": -16.885122688193963, "averageDeviationFromVwapPercent": 0.11379024399345643, "lastTradeAt": "2024-04-19T00:20:00Z"}, "attributes": {"spotMarkets": 374, "spotAssets": 349}}, {"id": "79fd918a-088c-4416-88f1-da7a8a593530", "serialId": 165, "name": "Exmo", "slug": "exmo", "exchangeType": "centralized", "marketData": {"volume24Hours": 22538118.943531998, "volume48To24Hours": 24664537.851109188, "percentChangeVolume24Hours": -8.621361245094498, "averageDeviationFromVwapPercent": 1.8240351100248586, "lastTradeAt": "2024-04-19T00:20:00Z"}, "attributes": {"spotMarkets": 117, "spotAssets": 50}}, {"id": "7ac870f5-a3ff-486d-a5a1-5d58140da970", "serialId": 267, "name": "BingX", "slug": "bingx", "exchangeType": "centralized", "marketData": {"volume24Hours": 808127819.2698442, "volume48To24Hours": 873881731.1702895, "percentChangeVolume24Hours": -7.5243490686535655, "averageDeviationFromVwapPercent": 0.0420525139699461, "lastTradeAt": "2024-04-19T00:20:00Z"}, "attributes": {"spotMarkets": 647, "spotAssets": 638}}, {"id": "7cb419ab-1236-4e40-8674-7317e4e4d108", "serialId": 3, "name": "BeQuant", "slug": "bequant", "exchangeType": "centralized", "marketData": {"volume24Hours": 260077154.44774193, "volume48To24Hours": 258168839.18384346, "percentChangeVolume24Hours": 0.7391733525747235, "averageDeviationFromVwapPercent": -0.04988198149731434, "lastTradeAt": "2024-04-19T00:20:00Z"}, "attributes": {"spotMarkets": 164, "spotAssets": 78}}, {"id": "7d2d72f0-b129-4845-bce2-23bb0058f0eb", "serialId": 103, "name": "Crypto.com", "slug": "crypto-com", "exchangeType": "centralized", "marketData": {"volume24Hours": 1295586095.5884342, "volume48To24Hours": 1354546844.2875175, "percentChangeVolume24Hours": -4.352802485033013, "averageDeviationFromVwapPercent": -0.08615910814237879, "lastTradeAt": "2024-04-19T00:20:00Z"}, "attributes": {"spotMarkets": 543, "spotAssets": 329}}, {"id": "8011d399-6f58-4b77-af4e-a0bd539d814a", "serialId": 248, "name": "Crema v2", "slug": "clmm-v2", "exchangeType": "decentralized", "marketData": {"volume24Hours": 0, "volume48To24Hours": 78705.95178445813, "percentChangeVolume24Hours": -100, "averageDeviationFromVwapPercent": -0.015104865650486512, "lastTradeAt": "2024-04-17T23:45:00Z"}, "attributes": {"spotMarkets": 5, "spotAssets": 5}}, {"id": "8048b31b-fa73-4d13-bf5c-43f6f834058c", "serialId": 160, "name": "Coinjar", "slug": "coinjar", "exchangeType": "centralized", "marketData": {"volume24Hours": 636439.0009520084, "volume48To24Hours": 1222504.3105722682, "percentChangeVolume24Hours": -47.93973359046202, "averageDeviationFromVwapPercent": 0.258528895166962, "lastTradeAt": "2024-04-19T00:17:00Z"}, "attributes": {"spotMarkets": 95, "spotAssets": 52}}, {"id": "8a1030cc-9b12-46e6-82d7-8b0a7e8f7f18", "serialId": 78, "name": "KuCoin", "slug": "kucoin", "exchangeType": "centralized", "marketData": {"volume24Hours": 851275925.9711719, "volume48To24Hours": 972659701.3055675, "percentChangeVolume24Hours": -12.479572780846826, "averageDeviationFromVwapPercent": 0.36728116044170056, "lastTradeAt": "2024-04-19T00:20:00Z"}, "attributes": {"spotMarkets": 1122, "spotAssets": 742}}, {"id": "8f192f0d-76fb-45f5-a40b-8882a3f2966d", "serialId": 83, "name": "Gemini", "slug": "gemini", "exchangeType": "centralized", "marketData": {"volume24Hours": 96939769.37026493, "volume48To24Hours": 120186805.28327224, "percentChangeVolume24Hours": -19.342419376416238, "averageDeviationFromVwapPercent": 1.851835220843147, "lastTradeAt": "2024-04-19T00:20:00Z"}, "attributes": {"spotMarkets": 98, "spotAssets": 77}}, {"id": "90bffaa1-cb56-4647-afb5-e67308bd9595", "serialId": 95, "name": "SpookySwap", "slug": "spookyswap", "exchangeType": "decentralized", "marketData": {"volume24Hours": 645849.5879867304, "volume48To24Hours": 1755186.3844871714, "percentChangeVolume24Hours": -63.203361552087586, "averageDeviationFromVwapPercent": -1.4645791294463026, "lastTradeAt": "2024-04-19T00:20:00Z"}, "attributes": {"spotMarkets": 131, "spotAssets": 90}}, {"id": "918dbe85-d025-4aa2-a9c5-41f09c09af34", "serialId": 82, "name": "Sushiswap", "slug": "sushiswap", "exchangeType": "decentralized", "marketData": {"volume24Hours": 9400431.407668024, "volume48To24Hours": 9774797.001094425, "percentChangeVolume24Hours": -3.829906578975352, "averageDeviationFromVwapPercent": 0.03223267970959831, "lastTradeAt": "2024-04-19T00:20:00Z"}, "attributes": {"spotMarkets": 635, "spotAssets": 426}}, {"id": "93b6bb16-5da8-4dd5-bc21-a7c4edf38260", "serialId": 259, "name": "Stepn", "slug": "stepn", "exchangeType": "decentralized", "marketData": {"volume24Hours": 1141591.957233709, "volume48To24Hours": 1163377.4903421095, "percentChangeVolume24Hours": -1.8726108498105833, "averageDeviationFromVwapPercent": -0.4171593200743551, "lastTradeAt": "2024-04-19T00:19:00Z"}, "attributes": {"spotMarkets": 4, "spotAssets": 5}}, {"id": "95425700-6ae5-4f3d-9fd3-720ad3922d1a", "serialId": 261, "name": "Invariant", "slug": "invariant", "exchangeType": "decentralized", "marketData": {"volume24Hours": 14067237.96722024, "volume48To24Hours": 5586302.5577172, "percentChangeVolume24Hours": 151.8166143326241, "averageDeviationFromVwapPercent": 0.16142396259850583, "lastTradeAt": "2024-04-19T00:20:00Z"}, "attributes": {"spotMarkets": 14, "spotAssets": 13}}, {"id": "9741f98b-7a9b-4564-921a-b52bf303fbfc", "serialId": 97, "name": "Gate.io", "slug": "gate-io", "exchangeType": "centralized", "marketData": {"volume24Hours": 2603069215.2306914, "volume48To24Hours": 2725964671.7136908, "percentChangeVolume24Hours": -4.508329024152045, "averageDeviationFromVwapPercent": -0.07948789695419625, "lastTradeAt": "2024-04-19T00:20:00Z"}, "attributes": {"spotMarkets": 2532, "spotAssets": 1590}}, {"id": "988f4f2c-b6d1-488d-ba31-821b00f80b64", "serialId": 149, "name": "bitFlyer EU", "slug": "bitflyer-eu", "exchangeType": "centralized", "marketData": {"volume24Hours": 105847862.56807697, "volume48To24Hours": 140245739.8028828, "percentChangeVolume24Hours": -24.526860696911353, "averageDeviationFromVwapPercent": 0.07053424739789, "lastTradeAt": "2024-04-19T00:20:00Z"}, "attributes": {"spotMarkets": 4, "spotAssets": 4}}, {"id": "9fa01e47-9330-4b8a-adc6-0b366954d0e0", "serialId": 47, "name": "bitFlyer", "slug": "bitflyer", "exchangeType": "centralized", "marketData": {"volume24Hours": 124566777.33753599, "volume48To24Hours": 161738766.82379577, "percentChangeVolume24Hours": -22.982733339840735, "averageDeviationFromVwapPercent": 0.43529262718224315, "lastTradeAt": "2024-04-19T00:20:00Z"}, "attributes": {"spotMarkets": 11, "spotAssets": 9}}, {"id": "9fcc188a-5b6c-49a6-b68c-4b9ffaa757e0", "serialId": 43, "name": "Coincheck", "slug": "coincheck", "exchangeType": "centralized", "marketData": {"volume24Hours": 112063296.85219485, "volume48To24Hours": 119174517.88710487, "percentChangeVolume24Hours": -5.967065074806134, "averageDeviationFromVwapPercent": -0.6221110775217192, "lastTradeAt": "2024-04-19T00:20:00Z"}, "attributes": {"spotMarkets": 3, "spotAssets": 4}}, {"id": "a77cae0e-d6f8-4865-8455-d6f737f428a9", "serialId": 151, "name": "bitFlyerFX", "slug": "bitflyerfx", "exchangeType": "centralized", "marketData": {"volume24Hours": 110084652.54765327, "volume48To24Hours": 168238255.18789923, "percentChangeVolume24Hours": -34.56621835223879, "averageDeviationFromVwapPercent": 0.02521486787527124, "lastTradeAt": "2024-04-19T00:20:00Z"}, "attributes": {"spotMarkets": 1, "spotAssets": 2}}, {"id": "ac6e5652-3e21-4515-b266-f7793dbcbb0a", "serialId": 50, "name": "Bitbank", "slug": "bitbank", "exchangeType": "centralized", "marketData": {"volume24Hours": 41948096.30059785, "volume48To24Hours": 46015780.38227401, "percentChangeVolume24Hours": -8.839758986773802, "averageDeviationFromVwapPercent": 0.17971281143736598, "lastTradeAt": "2024-04-19T00:20:00Z"}, "attributes": {"spotMarkets": 38, "spotAssets": 39}}, {"id": "b196e8a3-34cc-40bd-a6cb-bb8283958021", "serialId": 110, "name": "LATOKEN", "slug": "latoken", "exchangeType": "centralized", "marketData": {"volume24Hours": 715652487.1959505, "volume48To24Hours": 891728061.7640339, "percentChangeVolume24Hours": -19.74543385118634, "averageDeviationFromVwapPercent": 0.09750706094180976, "lastTradeAt": "2024-04-19T00:20:00Z"}, "attributes": {"spotMarkets": 654, "spotAssets": 526}}, {"id": "b78c172d-4e7b-4b52-ade2-6a78d60824bd", "serialId": 182, "name": "PancakeSwap (v3)", "slug": "pancakeswap-v3", "exchangeType": "decentralized", "marketData": {"volume24Hours": 402315814.0437104, "volume48To24Hours": 435879866.0002759, "percentChangeVolume24Hours": -7.70029876914394, "averageDeviationFromVwapPercent": -0.08434382962735966, "lastTradeAt": "2024-04-19T00:20:00Z"}, "attributes": {"spotMarkets": 854, "spotAssets": 577}}, {"id": "bc5bb7d7-fbf7-4039-a584-d4db59af66fa", "serialId": 26, "name": "Deribit", "slug": "deribit", "exchangeType": "centralized", "marketData": {"volume24Hours": 27260429.553599786, "volume48To24Hours": 53426881.82468935, "percentChangeVolume24Hours": -48.976192091745204, "averageDeviationFromVwapPercent": -0.025038436131981243, "lastTradeAt": "2024-04-19T00:20:00Z"}, "attributes": {"spotMarkets": 9, "spotAssets": 7}}, {"id": "bd9ed9e8-b95f-43e8-b156-654e62fc556f", "serialId": 113, "name": "XT.com", "slug": "xt-com", "exchangeType": "centralized", "marketData": {"volume24Hours": 724123820.7967131, "volume48To24Hours": 858023569.7809078, "percentChangeVolume24Hours": -15.605602654759856, "averageDeviationFromVwapPercent": 0.17716047510182004, "lastTradeAt": "2024-04-19T00:20:00Z"}, "attributes": {"spotMarkets": 610, "spotAssets": 540}}, {"id": "c3ccf24e-7e66-477f-b14c-9373908c9556", "serialId": 153, "name": "Bilaxy", "slug": "bilaxy", "exchangeType": "centralized", "marketData": {"volume24Hours": 306371047.370536, "volume48To24Hours": 255275610.87174386, "percentChangeVolume24Hours": 20.015792470070185, "averageDeviationFromVwapPercent": -0.26239918002741164, "lastTradeAt": "2024-04-19T00:20:00Z"}, "attributes": {"spotMarkets": 170, "spotAssets": 168}}, {"id": "c8369e58-3483-4599-a8c8-05ee281e1cd8", "serialId": 57, "name": "LMAX", "slug": "lmax", "exchangeType": "centralized", "marketData": {"volume24Hours": 206810970.085596, "volume48To24Hours": 251996899.10735157, "percentChangeVolume24Hours": -17.931144860042984, "averageDeviationFromVwapPercent": -0.059564826275849005, "lastTradeAt": "2024-04-19T00:20:00Z"}, "attributes": {"spotMarkets": 20, "spotAssets": 13}}, {"id": "c8bd2aad-04ee-4cea-8cbb-d1b700fdc7c4", "serialId": 81, "name": "Bibox", "slug": "bibox", "exchangeType": "centralized", "marketData": {"volume24Hours": 13362834.69483707, "volume48To24Hours": 14745136.40023439, "percentChangeVolume24Hours": -9.374628134164617, "averageDeviationFromVwapPercent": -0.4373425382698272, "lastTradeAt": "2024-04-19T00:20:00Z"}, "attributes": {"spotMarkets": 28, "spotAssets": 29}}, {"id": "c9bf3674-7f3f-48e5-8dda-fcfc192fdb84", "serialId": 48, "name": "Okcoin", "slug": "okcoin", "exchangeType": "centralized", "marketData": {"volume24Hours": 33503.249891, "volume48To24Hours": 35294.590877, "percentChangeVolume24Hours": -5.075398075140586, "averageDeviationFromVwapPercent": 4.23049285287732, "lastTradeAt": "2024-04-19T00:20:00Z"}, "attributes": {"spotMarkets": 2, "spotAssets": 3}}, {"id": "caf3b359-306b-48fa-89f1-69cf8d193842", "serialId": 171, "name": "Mercado Bitcoin", "slug": "mercado-bitcoin", "exchangeType": "centralized", "marketData": {"volume24Hours": 7299317.513984984, "volume48To24Hours": 9619982.46411732, "percentChangeVolume24Hours": -24.123380253430312, "averageDeviationFromVwapPercent": 0.49412931197739596, "lastTradeAt": "2024-04-19T00:20:00Z"}, "attributes": {"spotMarkets": 144, "spotAssets": 145}}, {"id": "cf7285e5-f572-4fb6-ac43-8bd0b655f69c", "serialId": 251, "name": "Saber", "slug": "saber-stableswap", "exchangeType": "decentralized", "marketData": {"volume24Hours": 8429734.699185733, "volume48To24Hours": 6045331.5869043255, "percentChangeVolume24Hours": 39.44205670118428, "averageDeviationFromVwapPercent": -0.03451709312454174, "lastTradeAt": "2024-04-19T00:19:00Z"}, "attributes": {"spotMarkets": 26, "spotAssets": 23}}, {"id": "d23554eb-4653-4997-bccf-a482a7e0471d", "serialId": 254, "name": "Mercurial", "slug": "mercurial", "exchangeType": "decentralized", "marketData": {"volume24Hours": 7798469.81168665, "volume48To24Hours": 4745886.287967929, "percentChangeVolume24Hours": 64.32062081760839, "averageDeviationFromVwapPercent": 0.05833514161692654, "lastTradeAt": "2024-04-19T00:20:00Z"}, "attributes": {"spotMarkets": 24, "spotAssets": 17}}, {"id": "d2701dfe-57af-4a26-85b4-633c665595a1", "serialId": 157, "name": "BTCMarkets", "slug": "btcmarkets", "exchangeType": "centralized", "marketData": {"volume24Hours": 8242.588718402427, "volume48To24Hours": 24659.51328209082, "percentChangeVolume24Hours": -66.57440629864875, "averageDeviationFromVwapPercent": 1.0016785682149592, "lastTradeAt": "2024-04-19T00:10:00Z"}, "attributes": {"spotMarkets": 2, "spotAssets": 3}}, {"id": "d3d5222e-83ab-4fc8-b253-91c5c36da163", "serialId": 98, "name": "ErisX", "slug": "erisx", "exchangeType": "centralized", "marketData": {"volume24Hours": 320169223.2063702, "volume48To24Hours": 368323723.08029085, "percentChangeVolume24Hours": -13.073960990403947, "averageDeviationFromVwapPercent": 0.19276824230010847, "lastTradeAt": "2024-04-19T00:20:00Z"}, "attributes": {"spotMarkets": 5, "spotAssets": 6}}, {"id": "d4baf95c-449b-4ac3-8244-b60ede12b5c3", "serialId": 249, "name": "Raydium (stable)", "slug": "raydium-stable", "exchangeType": "decentralized", "marketData": {"volume24Hours": 7666.869392187184, "volume48To24Hours": 4267.458974296294, "percentChangeVolume24Hours": 79.6588892445405, "averageDeviationFromVwapPercent": -0.035590925829547045, "lastTradeAt": "2024-04-18T22:44:00Z"}, "attributes": {"spotMarkets": 3, "spotAssets": 5}}, {"id": "d8a1337d-5629-4e0b-bda6-c04e4f101a22", "serialId": 1793789, "name": "Ubeswap", "slug": "ubeswap", "exchangeType": "decentralized", "marketData": {"volume24Hours": 11544.183359639517, "volume48To24Hours": 14962.846207281491, "percentChangeVolume24Hours": -22.847677509231648, "averageDeviationFromVwapPercent": 0.46332188233444105, "lastTradeAt": "2024-04-19T00:20:00Z"}, "attributes": {"spotMarkets": 21, "spotAssets": 15}}, {"id": "d8b0ea44-1963-451e-ac37-aead4ba3b4c7", "serialId": 68, "name": "Binance", "slug": "binance", "exchangeType": "centralized", "marketData": {"volume24Hours": 19625644471.913353, "volume48To24Hours": 25381911346.88572, "percentChangeVolume24Hours": -22.678618628453457, "averageDeviationFromVwapPercent": 0.011519681237064606, "lastTradeAt": "2024-04-19T00:20:00Z"}, "attributes": {"spotMarkets": 1263, "spotAssets": 401}}, {"id": "d8c2089f-56e1-4d97-884c-e093831fab02", "serialId": 263, "name": "Meteora", "slug": "meteora", "exchangeType": "decentralized", "marketData": {"volume24Hours": 28579330.67981988, "volume48To24Hours": 12074969.197952623, "percentChangeVolume24Hours": 136.68243132798764, "averageDeviationFromVwapPercent": 0.04096724639853703, "lastTradeAt": "2024-04-19T00:20:00Z"}, "attributes": {"spotMarkets": 549, "spotAssets": 268}}, {"id": "d8ddddb3-a4c4-4147-9615-9557a06e3d48", "serialId": 16, "name": "CoinMate", "slug": "coinmate", "exchangeType": "centralized", "marketData": {"volume24Hours": 320229.08376314124, "volume48To24Hours": 467220.00308166834, "percentChangeVolume24Hours": -31.4607504706586, "averageDeviationFromVwapPercent": 0.29380535575153766, "lastTradeAt": "2024-04-18T23:01:00Z"}, "attributes": {"spotMarkets": 11, "spotAssets": 8}}, {"id": "da3812b2-9038-420a-89e8-435322e4d8e2", "serialId": 89, "name": "Balancer (v1)", "slug": "balancer-v1", "exchangeType": "decentralized", "marketData": {"volume24Hours": 234538.11354144555, "volume48To24Hours": 323266.71268639475, "percentChangeVolume24Hours": -27.44749015684333, "averageDeviationFromVwapPercent": -0.12139196951168599, "lastTradeAt": "2024-04-19T00:12:00Z"}, "attributes": {"spotMarkets": 45, "spotAssets": 30}}, {"id": "dcb635f3-8289-4459-b883-b0a57948df18", "serialId": 77, "name": "Bitfinex", "slug": "bitfinex", "exchangeType": "centralized", "marketData": {"volume24Hours": 278704006.6654436, "volume48To24Hours": 450312737.2038728, "percentChangeVolume24Hours": -38.108788928334434, "averageDeviationFromVwapPercent": -0.0037465534887154506, "lastTradeAt": "2024-04-19T00:20:00Z"}, "attributes": {"spotMarkets": 344, "spotAssets": 170}}, {"id": "dd2aa49d-f334-4935-8eb2-9a75557e72c5", "serialId": 29, "name": "BtcTurk PRO", "slug": "btcturk", "exchangeType": "centralized", "marketData": {"volume24Hours": 100072217.11266784, "volume48To24Hours": 118449015.9868433, "percentChangeVolume24Hours": -15.514522194271887, "averageDeviationFromVwapPercent": -0.053780026904870694, "lastTradeAt": "2024-04-19T00:20:00Z"}, "attributes": {"spotMarkets": 211, "spotAssets": 107}}, {"id": "e262735b-1735-4f39-8c83-89d9e0d793a0", "serialId": 258, "name": "Orca v1", "slug": "orca-v1", "exchangeType": "decentralized", "marketData": {"volume24Hours": 32949.860743750316, "volume48To24Hours": 17420.31627939037, "percentChangeVolume24Hours": 89.14616827441097, "averageDeviationFromVwapPercent": -0.18308252554674037, "lastTradeAt": "2024-04-19T00:20:00Z"}, "attributes": {"spotMarkets": 15, "spotAssets": 14}}, {"id": "e7d8b017-a569-4843-b3d1-87aa2d4fcd5e", "serialId": 177, "name": "TimeX", "slug": "timex", "exchangeType": "centralized", "marketData": {"volume24Hours": 27110339.946595684, "volume48To24Hours": 32663643.493058197, "percentChangeVolume24Hours": -17.001482237101698, "averageDeviationFromVwapPercent": 0.4872436207090012, "lastTradeAt": "2024-04-19T00:20:00Z"}, "attributes": {"spotMarkets": 11, "spotAssets": 10}}, {"id": "e94a8c6a-1b4d-41e6-a381-1442f10a573e", "serialId": 71, "name": "Coinone", "slug": "coinone", "exchangeType": "centralized", "marketData": {"volume24Hours": 80522043.11971012, "volume48To24Hours": 92709658.09344359, "percentChangeVolume24Hours": -13.1460035819023, "averageDeviationFromVwapPercent": 0.5163205057334906, "lastTradeAt": "2024-04-19T00:20:00Z"}, "attributes": {"spotMarkets": 176, "spotAssets": 177}}, {"id": "e9adc72e-29fa-44b0-b937-3b7e334b414e", "serialId": 109, "name": "BTSE", "slug": "btse", "exchangeType": "centralized", "marketData": {"volume24Hours": 9511379.831947457, "volume48To24Hours": 15405396.505662069, "percentChangeVolume24Hours": -38.25942858107116, "averageDeviationFromVwapPercent": -0.07566844344010504, "lastTradeAt": "2024-04-19T00:20:00Z"}, "attributes": {"spotMarkets": 207, "spotAssets": 73}}, {"id": "eaad939f-52c1-4a08-9857-c520a01072cc", "serialId": 172, "name": "MEXC Global", "slug": "mexc", "exchangeType": "centralized", "marketData": {"volume24Hours": 1220231742.7554624, "volume48To24Hours": 1433842717.0854137, "percentChangeVolume24Hours": -14.897796793511663, "averageDeviationFromVwapPercent": 0.08390088327859198, "lastTradeAt": "2024-04-19T00:20:00Z"}, "attributes": {"spotMarkets": 1680, "spotAssets": 1562}}, {"id": "eabe49f0-c1a3-4166-b773-780fe809ac93", "serialId": 104, "name": "BitMart", "slug": "bitmart", "exchangeType": "centralized", "marketData": {"volume24Hours": 735142980.7410698, "volume48To24Hours": 948950862.8640113, "percentChangeVolume24Hours": -22.530975047290838, "averageDeviationFromVwapPercent": -0.09151066673005627, "lastTradeAt": "2024-04-19T00:20:00Z"}, "attributes": {"spotMarkets": 841, "spotAssets": 788}}, {"id": "ece516f1-1d90-4c13-b310-2e5b5196ea66", "serialId": 96, "name": "SpiritSwap", "slug": "spiritswap", "exchangeType": "decentralized", "marketData": {"volume24Hours": 33878.48396073489, "volume48To24Hours": 51714.841782130425, "percentChangeVolume24Hours": -34.48982382376488, "averageDeviationFromVwapPercent": -1.7932711429703054, "lastTradeAt": "2024-04-19T00:16:00Z"}, "attributes": {"spotMarkets": 48, "spotAssets": 38}}, {"id": "ee886717-7a45-4718-973a-93625a79a402", "serialId": 93, "name": "Trader Joe", "slug": "traderjoe", "exchangeType": "decentralized", "marketData": {"volume24Hours": 928079.9360643168, "volume48To24Hours": 1667521.0648794535, "percentChangeVolume24Hours": -44.34373540394175, "averageDeviationFromVwapPercent": -0.1928892254367587, "lastTradeAt": "2024-04-18T19:24:00Z"}, "attributes": {"spotMarkets": 104, "spotAssets": 79}}, {"id": "ef0a2432-f5d1-4675-ad6b-d566e9eeddfa", "serialId": 168, "name": "Independent Reserve", "slug": "independent-reserve", "exchangeType": "centralized", "marketData": {"volume24Hours": 6462353.747755238, "volume48To24Hours": 7513389.069782637, "percentChangeVolume24Hours": -13.988831301901497, "averageDeviationFromVwapPercent": 0.7490063417465387, "lastTradeAt": "2024-04-19T00:18:00Z"}, "attributes": {"spotMarkets": 19, "spotAssets": 20}}, {"id": "f06b8db0-bca0-4583-8f1d-5457ea5ea682", "serialId": 215, "name": "P2B", "slug": "P2B", "exchangeType": "centralized", "marketData": {"volume24Hours": 1654975840.2193928, "volume48To24Hours": 1874176322.2640471, "percentChangeVolume24Hours": -11.695830293056698, "averageDeviationFromVwapPercent": -0.02140992558995737, "lastTradeAt": "2024-04-19T00:20:00Z"}, "attributes": {"spotMarkets": 169, "spotAssets": 102}}, {"id": "f0ad2008-48e8-4bbc-9c21-54b1b38d7d6c", "serialId": 257, "name": "Raydium", "slug": "raydium-v4", "exchangeType": "decentralized", "marketData": {"volume24Hours": 143623585.84011194, "volume48To24Hours": 95666040.82029356, "percentChangeVolume24Hours": 50.13016594875659, "averageDeviationFromVwapPercent": 0.021131734988785567, "lastTradeAt": "2024-04-19T00:20:00Z"}, "attributes": {"spotMarkets": 1156, "spotAssets": 969}}, {"id": "f0b3d760-581b-4f2e-88d6-24dc925a6832", "serialId": 253, "name": "Orca", "slug": "orca-v2", "exchangeType": "decentralized", "marketData": {"volume24Hours": 2465735.4952337416, "volume48To24Hours": 1392915.165718314, "percentChangeVolume24Hours": 77.01978956932267, "averageDeviationFromVwapPercent": -0.09733827189299564, "lastTradeAt": "2024-04-19T00:20:00Z"}, "attributes": {"spotMarkets": 114, "spotAssets": 85}}, {"id": "f45c254f-8626-4d56-b18a-81c3bb40657e", "serialId": 152, "name": "BitTrade", "slug": "huobi-japan", "exchangeType": "centralized", "marketData": {"volume24Hours": 7574605.387906328, "volume48To24Hours": 5212116.493510785, "percentChangeVolume24Hours": 45.326862846156665, "averageDeviationFromVwapPercent": -0.120571463233098, "lastTradeAt": "2024-04-19T00:20:00Z"}, "attributes": {"spotMarkets": 34, "spotAssets": 33}}, {"id": "f475ccdc-cf1d-41af-843a-3359170e3db9", "serialId": 167, "name": "GOPAX", "slug": "gopax", "exchangeType": "centralized", "marketData": {"volume24Hours": 452612.0882433066, "volume48To24Hours": 291978.136550775, "percentChangeVolume24Hours": 55.01574658642203, "averageDeviationFromVwapPercent": 0.5910564084634308, "lastTradeAt": "2024-04-19T00:18:00Z"}, "attributes": {"spotMarkets": 41, "spotAssets": 38}}, {"id": "f494e80c-bdd5-477a-975a-a50f69bda728", "serialId": 55, "name": "BitMEX", "slug": "bitmex", "exchangeType": "centralized", "marketData": {"volume24Hours": 95326.15561451591, "volume48To24Hours": 206852.6713780764, "percentChangeVolume24Hours": -53.91591755647048, "averageDeviationFromVwapPercent": 0.752879402347125, "lastTradeAt": "2024-04-18T23:41:00Z"}, "attributes": {"spotMarkets": 12, "spotAssets": 12}}, {"id": "fa9a2579-646b-41ba-8ea1-5f0160fdb05e", "serialId": 36, "name": "Bitso", "slug": "bitso", "exchangeType": "centralized", "marketData": {"volume24Hours": 21808899.81595517, "volume48To24Hours": 31124366.792814434, "percentChangeVolume24Hours": -29.92982006306998, "averageDeviationFromVwapPercent": 0.1343017689150248, "lastTradeAt": "2024-04-19T00:20:00Z"}, "attributes": {"spotMarkets": 87, "spotAssets": 55}}, {"id": "fdbe583d-e1d9-4ff7-b1bb-1a602780dc23", "serialId": 260, "name": "Lifinity v1", "slug": "lifinity-v1", "exchangeType": "decentralized", "marketData": {"volume24Hours": 1463566.0263848577, "volume48To24Hours": 769816.7338905529, "percentChangeVolume24Hours": 90.11875969338661, "averageDeviationFromVwapPercent": 0.0409887262254124, "lastTradeAt": "2024-04-19T00:17:00Z"}, "attributes": {"spotMarkets": 2, "spotAssets": 4}}]